nanoid.py
nanoid/__init__.py
nanoid/algorithm.py
nanoid/generate.py
nanoid/method.py
nanoid/non_secure_generate.py
nanoid/resources.py
nanoid-2.0.0.dist-info/LICENSE
nanoid-2.0.0.dist-info/METADATA
nanoid-2.0.0.dist-info/WHEEL
nanoid-2.0.0.dist-info/top_level.txt
nanoid-2.0.0.dist-info/RECORD
