Metadata-Version: 2.1
Name: nanoid
Version: 2.0.0
Summary: A tiny, secure, URL-friendly, unique string ID generator for Python
Home-page: https://github.com/puyuan/py-nanoid
Author: Paul Yuan
Author-email: puyuan1@gmail.com
License: MIT
Platform: UNKNOWN
Classifier: License :: OSI Approved :: MIT License
Classifier: Programming Language :: Python
Classifier: Operating System :: OS Independent
Classifier: Topic :: Utilities
